<?xml version="1.0"?>
<ruleset name="BC Migration Ruleset">
    <description>BC Migration Ruleset</description>

    <!-- Include paths -->
    <file>src</file>

    <!-- Show progress, show error sources -->
    <arg value="ps" />
    <arg name="basepath" value="./" />
    <arg name="parallel" value="8" />

    <!-- Compatibility settings -->
    <config name="minimum_supported_wp_version" value="6.7" />
    <config name="testVersion" value="8.0-" />

    <!-- PHP Compatibility -->
    <rule ref="PHPCompatibility">
        <properties>
            <property name="testVersion" value="8.0-" />
        </properties>
    </rule>

    <!-- WordPress Coding Standards -->
	<rule ref="WordPress">
		<exclude name="WordPress.Files.FileName.NotHyphenatedLowercase" />
		<exclude name="WordPress.Files.FileName.InvalidClassFileName" />
        <exclude name="WordPress.WP.AlternativeFunctions.file_get_contents_file_get_contents" />
        <exclude name="WordPress.WP.AlternativeFunctions.file_system_operations_file_put_contents" />
        <exclude name="WordPress.WP.AlternativeFunctions.file_system_operations_mkdir" />
        <exclude name="WordPress.DB.DirectDatabaseQuery.DirectQuery" />
        <exclude name="WordPress.DB.PreparedSQL.InterpolatedNotPrepared" />
        <exclude name="WordPress.DB.DirectDatabaseQuery.NoCaching" />
	</rule>

    <!-- I18n -->
    <rule ref="WordPress.WP.I18n">
        <properties>
            <property name="text_domain" type="array" value="bc-migration" />
        </properties>
    </rule>
</ruleset>